atmigram/__init__.py
atmigram-0.0.1.dist-info/LICENSE
atmigram-0.0.1.dist-info/METADATA
atmigram-0.0.1.dist-info/WHEEL
atmigram-0.0.1.dist-info/top_level.txt
atmigram-0.0.1.dist-info/RECORD
