Metadata-Version: 2.1
Name: atmigram
Version: 0.0.1
Summary: async/await lib ... (atmigram)
Home-page: https://github.com/fishsouprecipe/atmigram
Author: fishsouprecipe
Author-email: fishsouprecipe@gmail.com
License: UNKNOWN
Platform: UNKNOWN
Classifier: Programming Language :: Python :: 3
Classifier: License :: OSI Approved :: MIT License
Classifier: Operating System :: OS Independent
Requires-Python: >=3.7.5
